argparse_color_formatter.py
argparse_color_formatter-2.0.0.post1.dist-info/LICENSE
argparse_color_formatter-2.0.0.post1.dist-info/METADATA
argparse_color_formatter-2.0.0.post1.dist-info/WHEEL
argparse_color_formatter-2.0.0.post1.dist-info/top_level.txt
argparse_color_formatter-2.0.0.post1.dist-info/RECORD
