Metadata-Version: 2.1
Name: argparse-color-formatter
Version: 2.0.0.post1
Summary: A `formatter_class` for `argparse` that deals with ANSI colour escapes. Specifically, this formatter does not count escape characters as displayed characters when wrapping `argparse`'s help text into the terminal.
Author-email: Arrai Innovations <support@arrai.com>
License: BSD 3-Clause License
Project-URL: repository, https://github.com/arrai-innovations/argparse-color-formatter/
Classifier: Development Status :: 6 - Mature
Classifier: Programming Language :: Python :: 3
Classifier: Programming Language :: Python :: 3.7
Classifier: Programming Language :: Python :: 3.8
Classifier: Programming Language :: Python :: 3.9
Classifier: Programming Language :: Python :: 3.10
Classifier: Programming Language :: Python :: 3.11
Classifier: Programming Language :: Python :: 3.12
Classifier: License :: OSI Approved :: BSD License
Classifier: Environment :: Console
Classifier: Intended Audience :: Developers
Requires-Python: >=3.5
License-File: LICENSE
Requires-Dist: ansicolors <2.0.0,>=1.1.8
